django_json_ordered/__init__.py
django_json_ordered/fields.py
django_json_ordered/meta.py
django_json_ordered-0.7.dist-info/LICENSE
django_json_ordered-0.7.dist-info/METADATA
django_json_ordered-0.7.dist-info/WHEEL
django_json_ordered-0.7.dist-info/top_level.txt
django_json_ordered-0.7.dist-info/RECORD
