Metadata-Version: 2.1
Name: django-json-ordered
Version: 0.7
Summary: It's an ordered json field
Home-page: https://github.com/rafaelgontijo/django-json-ordered
Author: Rafael Gontijo
Author-email: rafaelgontijowinter@gmail.com
License: MIT
Platform: UNKNOWN
Classifier: Environment :: Web Environment
Classifier: Framework :: Django
Classifier: Programming Language :: Python :: 3
Classifier: License :: OSI Approved :: MIT License
Classifier: Operating System :: OS Independent
Requires-Python: >=3.3
Requires-Dist: django (>=1.8.0)
Requires-Dist: psycopg2 (>=2.7.0)
